{
    "patient": "1103",
    "time_point": 1,
    "variants": [
        {
            "chromosome": "chr19",
            "crick_fourmer": {
                "C": {
                    "AACA": 4,
                    "AACC": 29,
                    "AACT": 1,
                    "AAGT": 4,
                    "ACAC": 3,
                    "ACCA": 18,
                    "ACCC": 28,
                    "ACCG": 7,
                    "ACCT": 1,
                    "ACGA": 5,
                    "ACGG": 8,
                    "ACGT": 5,
                    "ACTC": 9,
                    "AGCA": 1,
                    "AGGA": 2,
                    "AGGT": 2,
                    "CAAC": 5,
                    "CAAG": 2,
                    "CACA": 5,
                    "CACC": 23,
                    "CACG": 1,
                    "CACT": 5,
                    "CAGT": 4,
                    "CATG": 1,
                    "CCAC": 23,
                    "CCAT": 11,
                    "CCCG": 25,
                    "CCGA": 5,
                    "CCGC": 1,
                    "CCGG": 42,
                    "CCTA": 4,
                    "CCTC": 4,
                    "CGAC": 8,
                    "CGGA": 4,
                    "CGGC": 4,
                    "CGGG": 5,
                    "CGGT": 17,
                    "CGTA": 1,
                    "CGTC": 12,
                    "CTAC": 8,
                    "CTCC": 5,
                    "CTCG": 2,
                    "CTGG": 3,
                    "CTGT": 1,
                    "CTTC": 5,
                    "CTTG": 6,
                    "GAAC": 17,
                    "GACA": 2,
                    "GACC": 34,
                    "GACG": 14,
                    "GAGC": 3,
                    "GAGG": 5,
                    "GAGT": 2,
                    "GCAA": 10,
                    "GCAG": 7,
                    "GCCA": 4,
                    "GCCG": 2,
                    "GCGA": 2,
                    "GCGT": 2,
                    "GGAC": 13,
                    "GGCA": 5,
                    "GGCC": 1,
                    "GGCG": 4,
                    "GGGC": 12,
                    "GGGG": 2,
                    "GGTA": 3,
                    "GGTC": 1,
                    "GGTT": 5,
                    "GTAC": 25,
                    "GTAG": 4,
                    "GTCC": 11,
                    "GTCG": 11,
                    "GTGA": 2,
                    "GTGG": 16,
                    "GTGT": 2,
                    "GTTT": 1,
                    "TACC": 6,
                    "TACG": 3,
                    "TACT": 6,
                    "TAGG": 18,
                    "TAGT": 2,
                    "TCAC": 1,
                    "TCCC": 20,
                    "TCCG": 14,
                    "TCGG": 6,
                    "TCGT": 3,
                    "TCTG": 2,
                    "TGAC": 3,
                    "TGGA": 1,
                    "TGGT": 3,
                    "TGTA": 5,
                    "TGTC": 1,
                    "TTGT": 16,
                    "TTTC": 4
                },
                "G": {
                    "ACCC": 2,
                    "CACC": 2
                }
            },
            "fourmer": {
                "C": {
                    "AACA": 4,
                    "AACC": 29,
                    "AACT": 1,
                    "AAGT": 4,
                    "AATT": 2,
                    "ACAA": 4,
                    "ACAC": 8,
                    "ACAG": 1,
                    "ACAT": 1,
                    "ACCA": 18,
                    "ACCC": 32,
                    "ACCG": 10,
                    "ACCT": 10,
                    "ACGA": 5,
                    "ACGG": 8,
                    "ACGT": 5,
                    "ACTC": 9,
                    "ACTG": 4,
                    "ACTT": 2,
                    "AGAT": 1,
                    "AGCA": 1,
                    "AGCT": 2,
                    "AGGA": 5,
                    "AGGC": 2,
                    "AGGT": 2,
                    "AGTT": 1,
                    "ATAC": 1,
                    "ATGA": 2,
                    "ATGG": 2,
                    "ATTC": 1,
                    "CAAC": 6,
                    "CAAG": 2,
                    "CAAT": 21,
                    "CACA": 9,
                    "CACC": 33,
                    "CACG": 7,
                    "CACT": 15,
                    "CAGC": 2,
                    "CAGG": 2,
                    "CAGT": 4,
                    "CATG": 27,
                    "CCAC": 38,
                    "CCAG": 4,
                    "CCAT": 47,
                    "CCCA": 13,
                    "CCCC": 6,
                    "CCCG": 34,
                    "CCCT": 61,
                    "CCGA": 5,
                    "CCGC": 7,
                    "CCGG": 42,
                    "CCGT": 7,
                    "CCTA": 4,
                    "CCTC": 48,
                    "CCTG": 7,
                    "CCTT": 12,
                    "CGAA": 2,
                    "CGAC": 8,
                    "CGAT": 6,
                    "CGCA": 2,
                    "CGCC": 12,
                    "CGCT": 3,
                    "CGGA": 7,
                    "CGGC": 4,
                    "CGGG": 7,
                    "CGGT": 17,
                    "CGTA": 1,
                    "CGTC": 12,
                    "CGTG": 21,
                    "CTAC": 8,
                    "CTCA": 2,
                    "CTCC": 12,
                    "CTCG": 6,
                    "CTGC": 6,
                    "CTGG": 3,
                    "CTGT": 2,
                    "CTTC": 10,
                    "CTTG": 8,
                    "GAAC": 17,
                    "GAAG": 2,
                    "GAAT": 3,
                    "GACA": 16,
                    "GACC": 36,
                    "GACG": 15,
                    "GAGC": 3,
                    "GAGG": 8,
                    "GAGT": 2,
                    "GATA": 3,
                    "GATG": 3,
                    "GCAA": 10,
                    "GCAC": 6,
                    "GCAG": 10,
                    "GCCA": 4,
                    "GCCC": 9,
                    "GCCG": 3,
                    "GCGA": 5,
                    "GCGT": 2,
                    "GCTC": 26,
                    "GCTG": 5,
                    "GGAA": 2,
                    "GGAC": 17,
                    "GGAG": 16,
                    "GGAT": 8,
                    "GGCA": 10,
                    "GGCC": 6,
                    "GGCG": 25,
                    "GGGC": 13,
                    "GGGG": 6,
                    "GGGT": 4,
                    "GGTA": 6,
                    "GGTC": 1,
                    "GGTG": 12,
                    "GGTT": 5,
                    "GTAC": 25,
                    "GTAG": 11,
                    "GTCA": 1,
                    "GTCC": 11,
                    "GTCG": 13,
                    "GTGA": 2,
                    "GTGG": 17,
                    "GTGT": 2,
                    "GTTC": 1,
                    "GTTT": 1,
                    "TACC": 14,
                    "TACG": 3,
                    "TACT": 6,
                    "TAGG": 20,
                    "TAGT": 2,
                    "TCAA": 3,
                    "TCAC": 1,
                    "TCAT": 1,
                    "TCCA": 9,
                    "TCCC": 20,
                    "TCCG": 14,
                    "TCGG": 6,
                    "TCGT": 3,
                    "TCTC": 3,
                    "TCTG": 2,
                    "TGAC": 12,
                    "TGAG": 4,
                    "TGCC": 12,
                    "TGCT": 6,
                    "TGGA": 20,
                    "TGGG": 12,
                    "TGGT": 3,
                    "TGTA": 9,
                    "TGTC": 6,
                    "TTGT": 16,
                    "TTTC": 4
                },
                "G": {
                    "ACCC": 2,
                    "CACA": 2,
                    "CACC": 2,
                    "CCGT": 2
                }
            },
            "fragment_length": {
                "C": {
                    "109": 1,
                    "118": 1,
                    "119": 1,
                    "122": 1,
                    "124": 2,
                    "128": 2,
                    "130": 2,
                    "133": 2,
                    "134": 2,
                    "135": 1,
                    "136": 8,
                    "138": 1,
                    "139": 1,
                    "140": 5,
                    "141": 6,
                    "142": 5,
                    "143": 2,
                    "144": 1,
                    "145": 3,
                    "146": 8,
                    "148": 6,
                    "149": 6,
                    "150": 6,
                    "151": 5,
                    "152": 6,
                    "153": 1,
                    "154": 4,
                    "155": 11,
                    "156": 6,
                    "157": 7,
                    "158": 7,
                    "159": 6,
                    "160": 7,
                    "161": 19,
                    "162": 5,
                    "163": 14,
                    "164": 17,
                    "165": 14,
                    "166": 21,
                    "167": 21,
                    "168": 25,
                    "169": 25,
                    "170": 23,
                    "171": 17,
                    "172": 22,
                    "173": 20,
                    "174": 17,
                    "175": 17,
                    "176": 27,
                    "177": 16,
                    "178": 17,
                    "179": 14,
                    "180": 14,
                    "181": 14,
                    "182": 21,
                    "183": 12,
                    "184": 11,
                    "185": 7,
                    "186": 11,
                    "187": 2,
                    "188": 14,
                    "189": 5,
                    "190": 5,
                    "191": 9,
                    "192": 1,
                    "193": 8,
                    "194": 3,
                    "195": 8,
                    "196": 5,
                    "197": 4,
                    "198": 7,
                    "199": 2,
                    "201": 4,
                    "202": 7,
                    "203": 9,
                    "204": 3,
                    "205": 2,
                    "206": 3,
                    "207": 2,
                    "209": 2,
                    "210": 1,
                    "211": 2,
                    "212": 1,
                    "213": 3,
                    "214": 2,
                    "215": 4,
                    "216": 5,
                    "217": 2,
                    "218": 2,
                    "219": 3,
                    "224": 2,
                    "232": 1,
                    "233": 3,
                    "235": 3,
                    "236": 6,
                    "248": 1,
                    "254": 1,
                    "256": 1,
                    "257": 1,
                    "258": 3,
                    "267": 1,
                    "272": 2,
                    "273": 5,
                    "275": 1,
                    "276": 1,
                    "277": 1,
                    "278": 1,
                    "284": 4,
                    "285": 2,
                    "286": 1,
                    "287": 1,
                    "290": 2,
                    "291": 1,
                    "292": 5,
                    "293": 1,
                    "296": 2,
                    "297": 1,
                    "300": 1,
                    "302": 3,
                    "303": 2,
                    "304": 4,
                    "305": 1,
                    "307": 1,
                    "308": 1,
                    "309": 4,
                    "311": 2,
                    "312": 5,
                    "313": 3,
                    "314": 2,
                    "315": 1,
                    "316": 5,
                    "317": 2,
                    "318": 1,
                    "319": 4,
                    "320": 4,
                    "321": 1,
                    "323": 4,
                    "324": 2,
                    "325": 5,
                    "326": 3,
                    "327": 3,
                    "328": 4,
                    "329": 6,
                    "330": 3,
                    "331": 1,
                    "332": 1,
                    "333": 2,
                    "335": 3,
                    "338": 5,
                    "339": 3,
                    "340": 4,
                    "341": 3,
                    "343": 2,
                    "344": 1,
                    "346": 2,
                    "348": 2,
                    "349": 2,
                    "350": 3,
                    "352": 1,
                    "353": 2,
                    "354": 3,
                    "355": 1,
                    "357": 1,
                    "358": 2,
                    "361": 1,
                    "363": 2,
                    "364": 2,
                    "369": 1,
                    "371": 1
                },
                "G": {
                    "143": 2,
                    "171": 2
                }
            },
            "gene": "KEAP1",
            "position": 10499687,
            "variant_bases": [
                "G"
            ],
            "watson_fourmer": {
                "C": {
                    "AACA": 4,
                    "AACC": 29,
                    "AACT": 1,
                    "AAGT": 4,
                    "AATT": 2,
                    "ACAA": 4,
                    "ACAC": 8,
                    "ACAG": 1,
                    "ACAT": 1,
                    "ACCA": 18,
                    "ACCC": 32,
                    "ACCG": 10,
                    "ACCT": 10,
                    "ACGA": 5,
                    "ACGG": 8,
                    "ACGT": 5,
                    "ACTC": 9,
                    "ACTG": 4,
                    "ACTT": 2,
                    "AGAT": 1,
                    "AGCA": 1,
                    "AGCT": 2,
                    "AGGA": 5,
                    "AGGC": 2,
                    "AGGT": 2,
                    "AGTT": 1,
                    "ATAC": 1,
                    "ATGA": 2,
                    "ATGG": 2,
                    "ATTC": 1,
                    "CAAC": 6,
                    "CAAG": 2,
                    "CAAT": 21,
                    "CACA": 9,
                    "CACC": 33,
                    "CACG": 7,
                    "CACT": 15,
                    "CAGC": 2,
                    "CAGG": 2,
                    "CAGT": 4,
                    "CATG": 27,
                    "CCAC": 38,
                    "CCAG": 4,
                    "CCAT": 47,
                    "CCCA": 13,
                    "CCCC": 6,
                    "CCCG": 34,
                    "CCCT": 61,
                    "CCGA": 5,
                    "CCGC": 7,
                    "CCGG": 42,
                    "CCGT": 7,
                    "CCTA": 4,
                    "CCTC": 48,
                    "CCTG": 7,
                    "CCTT": 12,
                    "CGAA": 2,
                    "CGAC": 8,
                    "CGAT": 6,
                    "CGCA": 2,
                    "CGCC": 12,
                    "CGCT": 3,
                    "CGGA": 7,
                    "CGGC": 4,
                    "CGGG": 7,
                    "CGGT": 17,
                    "CGTA": 1,
                    "CGTC": 12,
                    "CGTG": 21,
                    "CTAC": 8,
                    "CTCA": 2,
                    "CTCC": 12,
                    "CTCG": 6,
                    "CTGC": 6,
                    "CTGG": 3,
                    "CTGT": 2,
                    "CTTC": 10,
                    "CTTG": 8,
                    "GAAC": 17,
                    "GAAG": 2,
                    "GAAT": 3,
                    "GACA": 16,
                    "GACC": 36,
                    "GACG": 15,
                    "GAGC": 3,
                    "GAGG": 8,
                    "GAGT": 2,
                    "GATA": 3,
                    "GATG": 3,
                    "GCAA": 10,
                    "GCAC": 6,
                    "GCAG": 10,
                    "GCCA": 4,
                    "GCCC": 9,
                    "GCCG": 3,
                    "GCGA": 5,
                    "GCGT": 2,
                    "GCTC": 26,
                    "GCTG": 5,
                    "GGAA": 2,
                    "GGAC": 17,
                    "GGAG": 16,
                    "GGAT": 8,
                    "GGCA": 10,
                    "GGCC": 6,
                    "GGCG": 25,
                    "GGGC": 13,
                    "GGGG": 6,
                    "GGGT": 4,
                    "GGTA": 6,
                    "GGTC": 1,
                    "GGTG": 12,
                    "GGTT": 5,
                    "GTAC": 25,
                    "GTAG": 11,
                    "GTCA": 1,
                    "GTCC": 11,
                    "GTCG": 13,
                    "GTGA": 2,
                    "GTGG": 17,
                    "GTGT": 2,
                    "GTTC": 1,
                    "GTTT": 1,
                    "TACC": 14,
                    "TACG": 3,
                    "TACT": 6,
                    "TAGG": 20,
                    "TAGT": 2,
                    "TCAA": 3,
                    "TCAC": 1,
                    "TCAT": 1,
                    "TCCA": 9,
                    "TCCC": 20,
                    "TCCG": 14,
                    "TCGG": 6,
                    "TCGT": 3,
                    "TCTC": 3,
                    "TCTG": 2,
                    "TGAC": 12,
                    "TGAG": 4,
                    "TGCC": 12,
                    "TGCT": 6,
                    "TGGA": 20,
                    "TGGG": 12,
                    "TGGT": 3,
                    "TGTA": 9,
                    "TGTC": 6,
                    "TTGT": 16,
                    "TTTC": 4
                },
                "G": {
                    "ACCC": 2,
                    "CACA": 2,
                    "CACC": 2,
                    "CCGT": 2
                }
            },
            "wild_type_base": "C"
        },
        {
            "chromosome": "chr12",
            "crick_fourmer": {
                "A": {
                    "CACT": 1,
                    "CTGC": 1,
                    "GTCG": 1,
                    "TGTA": 2
                },
                "C": {
                    "AAAA": 10,
                    "AAAG": 9,
                    "AAAT": 20,
                    "AACA": 1,
                    "AAGT": 16,
                    "AATA": 10,
                    "AATC": 11,
                    "AATT": 4,
                    "ACAC": 6,
                    "ACAG": 21,
                    "ACGA": 1,
                    "ACTG": 20,
                    "ACTT": 5,
                    "AGAT": 1,
                    "AGGT": 4,
                    "AGTA": 2,
                    "AGTC": 38,
                    "AGTG": 3,
                    "AGTT": 1,
                    "ATAA": 22,
                    "ATAC": 2,
                    "ATAG": 1,
                    "ATAT": 49,
                    "ATCT": 16,
                    "ATGA": 1,
                    "ATGG": 29,
                    "ATGT": 16,
                    "ATTA": 6,
                    "ATTC": 6,
                    "CAAA": 7,
                    "CACA": 1,
                    "CACT": 21,
                    "CAGT": 20,
                    "CATG": 1,
                    "CCAA": 1,
                    "CCGG": 11,
                    "CGAG": 6,
                    "CGGA": 2,
                    "CGTC": 6,
                    "CTGA": 18,
                    "CTGC": 3,
                    "CTTG": 17,
                    "CTTT": 6,
                    "GAAA": 4,
                    "GAAG": 1,
                    "GAAT": 10,
                    "GAGG": 35,
                    "GATA": 6,
                    "GATG": 1,
                    "GGAA": 10,
                    "GGAG": 3,
                    "GGTC": 9,
                    "GGTG": 13,
                    "GGTT": 1,
                    "GTAA": 1,
                    "GTAC": 8,
                    "GTAT": 3,
                    "GTCA": 23,
                    "GTCC": 7,
                    "GTCG": 56,
                    "GTGA": 1,
                    "GTGG": 57,
                    "GTGT": 41,
                    "GTTA": 3,
                    "GTTC": 4,
                    "GTTG": 9,
                    "GTTT": 4,
                    "TAAA": 7,
                    "TAAG": 26,
                    "TAAT": 22,
                    "TACA": 17,
                    "TACT": 29,
                    "TAGT": 10,
                    "TATA": 18,
                    "TATG": 3,
                    "TATT": 10,
                    "TCAA": 7,
                    "TCAG": 9,
                    "TCAT": 3,
                    "TCCA": 6,
                    "TCCG": 4,
                    "TCGA": 6,
                    "TCGT": 19,
                    "TCTG": 3,
                    "TCTT": 1,
                    "TGAG": 4,
                    "TGAT": 10,
                    "TGGA": 2,
                    "TGGT": 17,
                    "TGTA": 7,
                    "TGTG": 7,
                    "TGTT": 2,
                    "TTAA": 1,
                    "TTAC": 34,
                    "TTAG": 2,
                    "TTAT": 25,
                    "TTCA": 7,
                    "TTCC": 11,
                    "TTGA": 16,
                    "TTGT": 15,
                    "TTTA": 19,
                    "TTTG": 3,
                    "TTTT": 14
                }
            },
            "fourmer": {
                "A": {
                    "CACT": 1,
                    "CGTC": 1,
                    "CTAT": 1,
                    "CTGC": 1,
                    "GTCG": 1,
                    "TACC": 1,
                    "TGTA": 2,
                    "TTCT": 2
                },
                "C": {
                    "AAAA": 14,
                    "AAAC": 33,
                    "AAAG": 11,
                    "AAAT": 26,
                    "AACA": 15,
                    "AACC": 1,
                    "AAGA": 2,
                    "AAGG": 5,
                    "AAGT": 19,
                    "AATA": 15,
                    "AATC": 12,
                    "AATG": 4,
                    "AATT": 15,
                    "ACAA": 10,
                    "ACAC": 6,
                    "ACAG": 21,
                    "ACCA": 2,
                    "ACCC": 1,
                    "ACCT": 35,
                    "ACGA": 1,
                    "ACGC": 5,
                    "ACTC": 18,
                    "ACTG": 20,
                    "ACTT": 5,
                    "AGAA": 4,
                    "AGAG": 4,
                    "AGAT": 13,
                    "AGCT": 28,
                    "AGGA": 2,
                    "AGGC": 8,
                    "AGGT": 7,
                    "AGTA": 9,
                    "AGTC": 38,
                    "AGTG": 4,
                    "AGTT": 1,
                    "ATAA": 23,
                    "ATAC": 4,
                    "ATAG": 1,
                    "ATAT": 66,
                    "ATCA": 4,
                    "ATCG": 2,
                    "ATCT": 21,
                    "ATGA": 2,
                    "ATGG": 31,
                    "ATGT": 16,
                    "ATTA": 12,
                    "ATTC": 7,
                    "ATTG": 2,
                    "ATTT": 2,
                    "CAAA": 27,
                    "CAAG": 35,
                    "CACA": 6,
                    "CACC": 4,
                    "CACT": 31,
                    "CAGA": 4,
                    "CAGT": 20,
                    "CATA": 19,
                    "CATC": 1,
                    "CATG": 27,
                    "CCAA": 3,
                    "CCAC": 56,
                    "CCAG": 20,
                    "CCCA": 2,
                    "CCCT": 1,
                    "CCGG": 11,
                    "CCTA": 5,
                    "CCTC": 36,
                    "CCTG": 3,
                    "CCTT": 2,
                    "CGAA": 1,
                    "CGAG": 6,
                    "CGCC": 5,
                    "CGGA": 2,
                    "CGTC": 52,
                    "CTAC": 12,
                    "CTAG": 1,
                    "CTAT": 18,
                    "CTCA": 9,
                    "CTCT": 20,
                    "CTGA": 25,
                    "CTGC": 3,
                    "CTGT": 10,
                    "CTTA": 1,
                    "CTTG": 26,
                    "CTTT": 9,
                    "GAAA": 11,
                    "GAAG": 1,
                    "GAAT": 16,
                    "GACA": 1,
                    "GAGA": 9,
                    "GAGG": 35,
                    "GATA": 6,
                    "GATC": 10,
                    "GATG": 1,
                    "GATT": 12,
                    "GCAC": 6,
                    "GCAT": 14,
                    "GCCA": 4,
                    "GCCT": 22,
                    "GCTG": 26,
                    "GGAA": 10,
                    "GGAG": 3,
                    "GGAT": 5,
                    "GGCA": 16,
                    "GGTA": 1,
                    "GGTC": 20,
                    "GGTG": 13,
                    "GGTT": 1,
                    "GTAA": 2,
                    "GTAC": 8,
                    "GTAT": 21,
                    "GTCA": 23,
                    "GTCC": 13,
                    "GTCG": 56,
                    "GTGA": 1,
                    "GTGG": 57,
                    "GTGT": 41,
                    "GTTA": 3,
                    "GTTC": 4,
                    "GTTG": 9,
                    "GTTT": 4,
                    "TAAA": 18,
                    "TAAG": 30,
                    "TAAT": 27,
                    "TACA": 20,
                    "TACC": 12,
                    "TACG": 5,
                    "TACT": 30,
                    "TAGC": 2,
                    "TAGT": 10,
                    "TATA": 19,
                    "TATC": 36,
                    "TATG": 9,
                    "TATT": 44,
                    "TCAA": 15,
                    "TCAG": 15,
                    "TCAT": 13,
                    "TCCA": 14,
                    "TCCC": 1,
                    "TCCG": 4,
                    "TCCT": 5,
                    "TCGA": 6,
                    "TCGT": 21,
                    "TCTA": 12,
                    "TCTG": 12,
                    "TCTT": 22,
                    "TGAA": 10,
                    "TGAC": 4,
                    "TGAG": 4,
                    "TGAT": 15,
                    "TGCA": 13,
                    "TGCC": 8,
                    "TGGA": 8,
                    "TGGT": 17,
                    "TGTA": 18,
                    "TGTG": 7,
                    "TGTT": 12,
                    "TTAA": 3,
                    "TTAC": 36,
                    "TTAG": 11,
                    "TTAT": 28,
                    "TTCA": 7,
                    "TTCC": 11,
                    "TTCT": 8,
                    "TTGA": 16,
                    "TTGC": 1,
                    "TTGT": 16,
                    "TTTA": 20,
                    "TTTG": 3,
                    "TTTT": 14
                }
            },
            "fragment_length": {
                "A": {
                    "138": 3,
                    "152": 1,
                    "166": 1,
                    "207": 1,
                    "338": 1
                },
                "C": {
                    "99": 1,
                    "102": 1,
                    "103": 1,
                    "104": 1,
                    "106": 2,
                    "107": 1,
                    "110": 2,
                    "111": 1,
                    "112": 1,
                    "113": 1,
                    "117": 4,
                    "118": 1,
                    "119": 1,
                    "121": 2,
                    "123": 3,
                    "125": 3,
                    "126": 4,
                    "129": 4,
                    "131": 2,
                    "132": 6,
                    "133": 3,
                    "134": 7,
                    "135": 5,
                    "136": 4,
                    "137": 7,
                    "138": 5,
                    "139": 1,
                    "140": 13,
                    "141": 8,
                    "142": 7,
                    "143": 6,
                    "144": 16,
                    "145": 10,
                    "146": 7,
                    "147": 15,
                    "148": 15,
                    "149": 7,
                    "150": 8,
                    "151": 19,
                    "152": 12,
                    "153": 17,
                    "154": 16,
                    "155": 6,
                    "156": 13,
                    "157": 18,
                    "158": 18,
                    "159": 44,
                    "160": 12,
                    "161": 13,
                    "162": 16,
                    "163": 20,
                    "164": 41,
                    "165": 34,
                    "166": 31,
                    "167": 38,
                    "168": 25,
                    "169": 37,
                    "170": 41,
                    "171": 33,
                    "172": 38,
                    "173": 20,
                    "174": 43,
                    "175": 56,
                    "176": 19,
                    "177": 35,
                    "178": 36,
                    "179": 33,
                    "180": 22,
                    "181": 12,
                    "182": 17,
                    "183": 30,
                    "184": 11,
                    "185": 22,
                    "186": 10,
                    "187": 15,
                    "188": 21,
                    "189": 11,
                    "190": 16,
                    "191": 9,
                    "192": 4,
                    "193": 7,
                    "194": 7,
                    "195": 13,
                    "196": 13,
                    "197": 11,
                    "198": 5,
                    "199": 13,
                    "200": 8,
                    "201": 8,
                    "202": 14,
                    "203": 4,
                    "204": 4,
                    "205": 5,
                    "206": 2,
                    "207": 4,
                    "209": 7,
                    "210": 2,
                    "211": 5,
                    "212": 7,
                    "213": 3,
                    "214": 7,
                    "215": 3,
                    "216": 2,
                    "217": 4,
                    "218": 2,
                    "219": 4,
                    "220": 9,
                    "222": 4,
                    "224": 4,
                    "225": 2,
                    "226": 3,
                    "228": 2,
                    "230": 1,
                    "232": 2,
                    "236": 3,
                    "239": 6,
                    "241": 2,
                    "242": 2,
                    "243": 1,
                    "251": 2,
                    "252": 2,
                    "255": 1,
                    "257": 4,
                    "260": 1,
                    "261": 1,
                    "273": 1,
                    "278": 2,
                    "284": 1,
                    "285": 2,
                    "288": 1,
                    "289": 3,
                    "291": 1,
                    "293": 3,
                    "295": 4,
                    "296": 1,
                    "298": 1,
                    "300": 3,
                    "301": 6,
                    "302": 3,
                    "304": 1,
                    "305": 2,
                    "307": 2,
                    "308": 3,
                    "309": 13,
                    "310": 3,
                    "311": 2,
                    "312": 4,
                    "315": 3,
                    "317": 1,
                    "319": 1,
                    "321": 3,
                    "322": 2,
                    "323": 1,
                    "324": 4,
                    "325": 4,
                    "326": 6,
                    "327": 6,
                    "328": 3,
                    "329": 2,
                    "330": 2,
                    "331": 7,
                    "332": 3,
                    "333": 3,
                    "335": 3,
                    "336": 4,
                    "337": 6,
                    "340": 1,
                    "341": 5,
                    "342": 5,
                    "343": 1,
                    "344": 6,
                    "347": 2,
                    "348": 4,
                    "349": 3,
                    "350": 3,
                    "351": 4,
                    "352": 5,
                    "354": 1,
                    "355": 2,
                    "359": 3,
                    "363": 1,
                    "364": 2,
                    "369": 1
                }
            },
            "gene": "KRAS",
            "position": 25245350,
            "variant_bases": [
                "A"
            ],
            "watson_fourmer": {
                "A": {
                    "CACT": 1,
                    "CGTC": 1,
                    "CTAT": 1,
                    "CTGC": 1,
                    "GTCG": 1,
                    "TACC": 1,
                    "TGTA": 2,
                    "TTCT": 2
                },
                "C": {
                    "AAAA": 14,
                    "AAAC": 33,
                    "AAAG": 11,
                    "AAAT": 26,
                    "AACA": 15,
                    "AACC": 1,
                    "AAGA": 2,
                    "AAGG": 5,
                    "AAGT": 19,
                    "AATA": 15,
                    "AATC": 12,
                    "AATG": 4,
                    "AATT": 15,
                    "ACAA": 10,
                    "ACAC": 6,
                    "ACAG": 21,
                    "ACCA": 2,
                    "ACCC": 1,
                    "ACCT": 35,
                    "ACGA": 1,
                    "ACGC": 5,
                    "ACTC": 18,
                    "ACTG": 20,
                    "ACTT": 5,
                    "AGAA": 4,
                    "AGAG": 4,
                    "AGAT": 13,
                    "AGCT": 28,
                    "AGGA": 2,
                    "AGGC": 8,
                    "AGGT": 7,
                    "AGTA": 9,
                    "AGTC": 38,
                    "AGTG": 4,
                    "AGTT": 1,
                    "ATAA": 23,
                    "ATAC": 4,
                    "ATAG": 1,
                    "ATAT": 66,
                    "ATCA": 4,
                    "ATCG": 2,
                    "ATCT": 21,
                    "ATGA": 2,
                    "ATGG": 31,
                    "ATGT": 16,
                    "ATTA": 12,
                    "ATTC": 7,
                    "ATTG": 2,
                    "ATTT": 2,
                    "CAAA": 27,
                    "CAAG": 35,
                    "CACA": 6,
                    "CACC": 4,
                    "CACT": 31,
                    "CAGA": 4,
                    "CAGT": 20,
                    "CATA": 19,
                    "CATC": 1,
                    "CATG": 27,
                    "CCAA": 3,
                    "CCAC": 56,
                    "CCAG": 20,
                    "CCCA": 2,
                    "CCCT": 1,
                    "CCGG": 11,
                    "CCTA": 5,
                    "CCTC": 36,
                    "CCTG": 3,
                    "CCTT": 2,
                    "CGAA": 1,
                    "CGAG": 6,
                    "CGCC": 5,
                    "CGGA": 2,
                    "CGTC": 52,
                    "CTAC": 12,
                    "CTAG": 1,
                    "CTAT": 18,
                    "CTCA": 9,
                    "CTCT": 20,
                    "CTGA": 25,
                    "CTGC": 3,
                    "CTGT": 10,
                    "CTTA": 1,
                    "CTTG": 26,
                    "CTTT": 9,
                    "GAAA": 11,
                    "GAAG": 1,
                    "GAAT": 16,
                    "GACA": 1,
                    "GAGA": 9,
                    "GAGG": 35,
                    "GATA": 6,
                    "GATC": 10,
                    "GATG": 1,
                    "GATT": 12,
                    "GCAC": 6,
                    "GCAT": 14,
                    "GCCA": 4,
                    "GCCT": 22,
                    "GCTG": 26,
                    "GGAA": 10,
                    "GGAG": 3,
                    "GGAT": 5,
                    "GGCA": 16,
                    "GGTA": 1,
                    "GGTC": 20,
                    "GGTG": 13,
                    "GGTT": 1,
                    "GTAA": 2,
                    "GTAC": 8,
                    "GTAT": 21,
                    "GTCA": 23,
                    "GTCC": 13,
                    "GTCG": 56,
                    "GTGA": 1,
                    "GTGG": 57,
                    "GTGT": 41,
                    "GTTA": 3,
                    "GTTC": 4,
                    "GTTG": 9,
                    "GTTT": 4,
                    "TAAA": 18,
                    "TAAG": 30,
                    "TAAT": 27,
                    "TACA": 20,
                    "TACC": 12,
                    "TACG": 5,
                    "TACT": 30,
                    "TAGC": 2,
                    "TAGT": 10,
                    "TATA": 19,
                    "TATC": 36,
                    "TATG": 9,
                    "TATT": 44,
                    "TCAA": 15,
                    "TCAG": 15,
                    "TCAT": 13,
                    "TCCA": 14,
                    "TCCC": 1,
                    "TCCG": 4,
                    "TCCT": 5,
                    "TCGA": 6,
                    "TCGT": 21,
                    "TCTA": 12,
                    "TCTG": 12,
                    "TCTT": 22,
                    "TGAA": 10,
                    "TGAC": 4,
                    "TGAG": 4,
                    "TGAT": 15,
                    "TGCA": 13,
                    "TGCC": 8,
                    "TGGA": 8,
                    "TGGT": 17,
                    "TGTA": 18,
                    "TGTG": 7,
                    "TGTT": 12,
                    "TTAA": 3,
                    "TTAC": 36,
                    "TTAG": 11,
                    "TTAT": 28,
                    "TTCA": 7,
                    "TTCC": 11,
                    "TTCT": 8,
                    "TTGA": 16,
                    "TTGC": 1,
                    "TTGT": 16,
                    "TTTA": 20,
                    "TTTG": 3,
                    "TTTT": 14
                }
            },
            "wild_type_base": "C"
        }
    ]
}